rendre/__init__.py
rendre/__main__.py
rendre/api.py
rendre/core.py
rendre/utils.py
rendre/report/__init__.py
rendre/report/filters.py
rendre/report/tmpl_0002.py
rendre/report/tmpl_0001/__init__.py
rendre/report/tmpl_0001/build_filters.html
rendre/report/tmpl_0001/main.html
rendre/report/tmpl_0001/single_item.html
rendre/report/tmpl_0003/__init__ copy.py
rendre/report/tmpl_0003/__init__.py
rendre/report/tmpl_0003/main.html
rendre/report/tmpl_0003/main.tex
rendre/report/tmpl_0003/single_item.html
rendre/report/tmpl_0003/single_item.tex
rendre/report/tmpl_0004/__init__.py
rendre/report/tmpl_0004/main.html
rendre/report/tmpl_0004/single_item.html
rendre/report/tmpl_0005/__init__.py
rendre/report/tmpl_0005/main.html
rendre/report/tmpl_0005/single_item.html
rendre/report/tmpl_0006/__init__.py
rendre/report/tmpl_0006/build_filters.html
rendre/report/tmpl_0006/main.html
rendre/report/tmpl_0006/single_item.html
rendre/report/tmpl_0008/__init__.py
rendre/sphinx/__init__.py
rendre-0.0.14.dist-info/METADATA
rendre-0.0.14.dist-info/WHEEL
rendre-0.0.14.dist-info/entry_points.txt
rendre-0.0.14.dist-info/top_level.txt
rendre-0.0.14.dist-info/RECORD
