Metadata-Version: 2.1
Name: rendre
Version: 0.0.14
Summary: Utilities
Home-page: https://github.com/claudioperez/rendre
Author: Claudio Perez
Author-email: claudio_perez@berkeley.edu
License: UNKNOWN
Platform: UNKNOWN
Classifier: Programming Language :: Python :: 3
Classifier: Operating System :: OS Independent
Requires-Dist: coloredlogs
Requires-Dist: aurore (>0.0.8)
Requires-Dist: pyyaml
Requires-Dist: jinja2
